galapy/CompositeStellarPopulation.py
galapy/Cosmology.py
galapy/NFF_core.cpython-38-x86_64-linux-gnu.so
galapy/InterGalacticMedium.py
galapy/InterStellarMedium.py
galapy/Synchrotron.py
galapy/PhotometricSystem.py
galapy/SYN_core.cpython-38-x86_64-linux-gnu.so
galapy/Noise.py
galapy/Galaxy.py
galapy/BandpassTransmission.cpython-38-x86_64-linux-gnu.so
galapy/Handlers.py
galapy/__init__.py
galapy/ISM_core.cpython-38-x86_64-linux-gnu.so
galapy/SFH_core.cpython-38-x86_64-linux-gnu.so
galapy/CSP_core.cpython-38-x86_64-linux-gnu.so
galapy/StarFormationHistory.py
galapy/XRayBinaries.py
galapy/ActiveGalacticNucleus.py
galapy/NebularFreeFree.py
galapy/configuration/filesystem.py
galapy/configuration/__init__.py
galapy/configuration/configure.py
galapy/sampling/Observation.py
galapy/sampling/Run.py
galapy/sampling/Results.py
galapy/sampling/Sampler.py
galapy/sampling/Statistics.py
galapy/sampling/__init__.py
galapy/analysis/plot.py
galapy/analysis/__init__.py
galapy/analysis/funcs.py
galapy/io/__init__.py
galapy/io/hdf5.py
galapy/internal/globs.py
galapy/internal/constants.py
galapy/internal/data.py
galapy/internal/__init__.py
galapy/internal/abc.py
galapy/internal/utils.py
galapy/internal/interp.cpython-38-x86_64-linux-gnu.so
galapy_fit-0.5.3.dist-info/LICENSE
galapy_fit-0.5.3.dist-info/METADATA
galapy_fit-0.5.3.dist-info/RECORD
galapy_fit-0.5.3.dist-info/top_level.txt
galapy_fit-0.5.3.dist-info/entry_points.txt
galapy_fit-0.5.3.dist-info/WHEEL
