Metadata-Version: 2.1
Name: galapy-fit
Version: 0.5.3
Summary: GalaPy - Spectral modelling tool for galaxies in Python
Author-email: Tommaso Ronconi <tronconi@sissa.it>
License: GNU GENERAL PUBLIC LICENSE
Project-URL: Source, https://github.com/TommasoRonconi/galapy
Project-URL: Documentation, http://galapy.readthedocs.io/
Classifier: License :: OSI Approved :: GNU General Public License v3 or later (GPLv3+)
Classifier: Operating System :: POSIX :: Linux
Classifier: Operating System :: MacOS
Classifier: Programming Language :: Python
Classifier: Programming Language :: Python :: 3
Classifier: Programming Language :: C++
Requires-Python: >=3.7
License-File: LICENSE
Requires-Dist: numpy
Requires-Dist: scipy
Requires-Dist: tqdm
Requires-Dist: emcee
Requires-Dist: dynesty
Requires-Dist: matplotlib >=3.6
Requires-Dist: getdist
Requires-Dist: requests
Requires-Dist: h5py
Provides-Extra: dev
Requires-Dist: bumpver ; extra == 'dev'
Requires-Dist: pytest ; extra == 'dev'
Provides-Extra: doc
Requires-Dist: sphinx ; extra == 'doc'
Requires-Dist: sphinx-rtd-theme ; extra == 'doc'
Requires-Dist: jinja >=3.0.0 ; extra == 'doc'
Requires-Dist: nbsphinx ; extra == 'doc'
Requires-Dist: graphviz ; extra == 'doc'
Provides-Extra: test
Requires-Dist: pytest ; extra == 'test'
